sub2nan-0.1.0.dist-info/licenses/LICENSE
subtitle_utils/__init__.py
subtitle_utils/exceptions.py
subtitle_utils/srt_handler.py
sub2nan-0.1.0.dist-info/METADATA
sub2nan-0.1.0.dist-info/WHEEL
sub2nan-0.1.0.dist-info/top_level.txt
sub2nan-0.1.0.dist-info/RECORD
